markov_draftjs/__init__.py
markov_draftjs/content.json
tests/__init__.py
tests/test_markov_draftjs.py
markov_draftjs-0.2.0.dist-info/LICENSE
markov_draftjs-0.2.0.dist-info/METADATA
markov_draftjs-0.2.0.dist-info/WHEEL
markov_draftjs-0.2.0.dist-info/top_level.txt
markov_draftjs-0.2.0.dist-info/RECORD
