Metadata-Version: 2.1
Name: markov_draftjs
Version: 0.2.0
Summary: Draft.js sample content generated with Markov chains of Project Gutenberg books.
Home-page: https://github.com/thibaudcolas/markov_draftjs
Author: Thibaud Colas
Author-email: thibaudcolas@gmail.com
License: MIT
Keywords: draftjs,editor,markov,content
Platform: UNKNOWN
Classifier: Environment :: Web Environment
Classifier: Intended Audience :: Developers
Classifier: License :: OSI Approved :: MIT License
Classifier: Operating System :: OS Independent
Classifier: Programming Language :: Python
Classifier: Programming Language :: Python :: 3
Classifier: Topic :: Internet :: WWW/HTTP
Classifier: Topic :: Internet :: WWW/HTTP :: Dynamic Content
Classifier: Topic :: Internet :: WWW/HTTP :: Site Management
Classifier: Topic :: Software Development :: Libraries :: Application Frameworks
Classifier: Topic :: Software Development :: Libraries :: Python Modules
Classifier: Topic :: Text Editors :: Word Processors
License-File: LICENSE
